{
  "id": "3e96eaf5-ea88-442f-8e6a-0d4e94191736",
  "parentId": "7d1e1eb3-e343-4809-b676-915d346f11a8",
  "rootParentId": "7d1e1eb3-e343-4809-b676-915d346f11a8",
  "name": "2-AmusementPark-text",
  "auto": true,
  "contexts": [
    "text-2"
  ],
  "responses": [
    {
      "resetContexts": false,
      "action": "DeleteAllContexts",
      "affectedContexts": [],
      "parameters": [
        {
          "id": "d0b49473-18ce-4d50-bbbc-1c5f748587ba",
          "required": false,
          "dataType": "@sys.any",
          "name": "text-name",
          "value": "Этот текст называется \"Парк развлечений\".",
          "promptMessages": [],
          "noMatchPromptMessages": [],
          "noInputPromptMessages": [],
          "outputDialogContexts": [],
          "isList": false
        },
        {
          "id": "e60fcccf-3fc7-4611-8212-b0e4a55e03ff",
          "required": true,
          "dataType": "@sys.any",
          "name": "human",
          "value": "$human",
          "prompts": [
            {
              "lang": "ru",
              "value": "Для начала назови имя своего друга или известного артиста"
            },
            {
              "lang": "ru",
              "value": "Назови имя своего друга или известного актёра"
            },
            {
              "lang": "ru",
              "value": "Скажи имя своего друга или известного актёра"
            }
          ],
          "promptMessages": [],
          "noMatchPromptMessages": [],
          "noInputPromptMessages": [],
          "outputDialogContexts": [],
          "isList": false
        },
        {
          "id": "37c51d44-d620-44ff-91e2-812886e0d448",
          "required": true,
          "dataType": "@sys.any",
          "name": "thing",
          "value": "$thing",
          "prompts": [
            {
              "lang": "ru",
              "value": "Предмет мужского рода"
            },
            {
              "lang": "ru",
              "value": "Назови предмет мужского рода"
            }
          ],
          "promptMessages": [],
          "noMatchPromptMessages": [],
          "noInputPromptMessages": [],
          "outputDialogContexts": [],
          "isList": false
        },
        {
          "id": "17d19e1c-9ea8-49c8-a8d7-38b8f64a5905",
          "required": true,
          "dataType": "@sys.any",
          "name": "things",
          "value": "$things",
          "prompts": [
            {
              "lang": "ru",
              "value": "Предмет во множественном числе"
            },
            {
              "lang": "ru",
              "value": "Теперь назови предмет во множественном числе"
            }
          ],
          "promptMessages": [],
          "noMatchPromptMessages": [],
          "noInputPromptMessages": [],
          "outputDialogContexts": [],
          "isList": false
        },
        {
          "id": "f6628e05-d5c7-4494-ab47-932eaa45289b",
          "required": true,
          "dataType": "@sys.any",
          "name": "animals",
          "value": "$animals",
          "prompts": [
            {
              "lang": "ru",
              "value": "Теперь назови животное во множественном числе"
            },
            {
              "lang": "ru",
              "value": "Назови животное во множественном числе"
            }
          ],
          "promptMessages": [],
          "noMatchPromptMessages": [],
          "noInputPromptMessages": [],
          "outputDialogContexts": [],
          "isList": false
        },
        {
          "id": "2d18bcf4-7bdb-43d2-86d5-39ee69e243e9",
          "required": true,
          "dataType": "@sys.any",
          "name": "adjectives-1",
          "value": "$adjectives-1",
          "prompts": [
            {
              "lang": "ru",
              "value": "Теперь просто отвечай на вопросы первое, что приходит в голову. Итак - \"какие\"?"
            },
            {
              "lang": "ru",
              "value": "Теперь отвечай на вопросы первое, что приходит в голову. Итак - \"какие\"?"
            }
          ],
          "promptMessages": [],
          "noMatchPromptMessages": [],
          "noInputPromptMessages": [],
          "outputDialogContexts": [],
          "isList": false
        },
        {
          "id": "f2c908e3-2056-4934-baed-5c9ef9ad7a1c",
          "required": true,
          "dataType": "@sys.any",
          "name": "actions-1",
          "value": "$actions-1",
          "prompts": [
            {
              "lang": "ru",
              "value": "\"Что делали\"?"
            },
            {
              "lang": "ru",
              "value": "Дальше - \"что делали\"?"
            }
          ],
          "promptMessages": [],
          "noMatchPromptMessages": [],
          "noInputPromptMessages": [],
          "outputDialogContexts": [],
          "isList": false
        },
        {
          "id": "e45441ba-372e-4c7f-9083-71b22cc334a2",
          "required": true,
          "dataType": "@sys.any",
          "name": "adjective-male",
          "value": "$adjective-male",
          "prompts": [
            {
              "lang": "ru",
              "value": "\"Какой\"?"
            }
          ],
          "promptMessages": [],
          "noMatchPromptMessages": [],
          "noInputPromptMessages": [],
          "outputDialogContexts": [],
          "isList": false
        },
        {
          "id": "6d6d72d5-aa16-4b87-bea6-c7ea9c1ad574",
          "required": true,
          "dataType": "@sys.any",
          "name": "actions-2",
          "value": "$actions-2",
          "prompts": [
            {
              "lang": "ru",
              "value": "\"Что сделали\"?"
            }
          ],
          "promptMessages": [],
          "noMatchPromptMessages": [],
          "noInputPromptMessages": [],
          "outputDialogContexts": [],
          "isList": false
        },
        {
          "id": "ab739503-b792-4e07-96cd-5094d27e10ea",
          "required": true,
          "dataType": "@sys.any",
          "name": "adjectives-2",
          "value": "$adjectives-2",
          "prompts": [
            {
              "lang": "ru",
              "value": "\"Какие\"?"
            }
          ],
          "promptMessages": [],
          "noMatchPromptMessages": [],
          "noInputPromptMessages": [],
          "outputDialogContexts": [],
          "isList": false
        },
        {
          "id": "33cb5982-1bff-4f39-aeda-05eae01b60ef",
          "required": true,
          "dataType": "@sys.any",
          "name": "actions-3",
          "value": "$actions-3",
          "prompts": [
            {
              "lang": "ru",
              "value": "\"Что делать\"? (из нескольких слов)"
            }
          ],
          "promptMessages": [],
          "noMatchPromptMessages": [],
          "noInputPromptMessages": [],
          "outputDialogContexts": [],
          "isList": false
        },
        {
          "id": "385fc8e6-f453-468c-a584-43e8281babd1",
          "required": true,
          "dataType": "@sys.any",
          "name": "actions-4",
          "value": "$actions-4",
          "prompts": [
            {
              "lang": "ru",
              "value": "Ещё раз \"что делать\"?"
            }
          ],
          "promptMessages": [],
          "noMatchPromptMessages": [],
          "noInputPromptMessages": [],
          "outputDialogContexts": [],
          "isList": false
        },
        {
          "id": "f434869c-31af-4265-8c53-92747a387d35",
          "required": true,
          "dataType": "@sys.any",
          "name": "actions-5",
          "value": "$actions-5",
          "prompts": [
            {
              "lang": "ru",
              "value": "Снова - \"Что делать\"?"
            }
          ],
          "promptMessages": [],
          "noMatchPromptMessages": [],
          "noInputPromptMessages": [],
          "outputDialogContexts": [],
          "isList": false
        },
        {
          "id": "3928baab-9b2f-4e73-a230-bc4abaf4aab5",
          "required": true,
          "dataType": "@sys.any",
          "name": "where",
          "value": "$where",
          "prompts": [
            {
              "lang": "ru",
              "value": "И последний - \"Где\"?"
            }
          ],
          "promptMessages": [],
          "noMatchPromptMessages": [],
          "noInputPromptMessages": [],
          "outputDialogContexts": [],
          "isList": false
        }
      ],
      "messages": [
        {
          "type": 0,
          "lang": "ru",
          "condition": "",
          "speech": "Слушай, что получилось: В прошлом месяце я ездил в парк развлечений с другом по имени $human.\nТам были $adjectives-1 люди, которые повсюду $actions-1. Были там и чудаки в карнавальных костюмах - ну, настоящие $animals. Один из них надел мне на голову $adjective-male $thing, и мы $actions-2 от такого нахальства.\nПотом мы покатались на аттракционе $adjectives-2 горки, которые почему-то назывались Волшебные $things. $human совсем ошалел от этих горок, и мы решили $actions-3. Потом мы поехали в гостиницу и стали там $actions-4.\nЕще мне хочется отдохнуть $where. Поедем туда на следующий год и будем там вовсю $actions-5."
        }
      ],
      "defaultResponsePlatforms": {},
      "speech": []
    }
  ],
  "priority": 500000,
  "webhookUsed": false,
  "webhookForSlotFilling": false,
  "fallbackIntent": false,
  "events": [
    {
      "name": "text-2"
    }
  ],
  "conditionalResponses": [],
  "condition": "",
  "conditionalFollowupEvents": []
}