[
  {
    "id": "1c1eff4b-5103-4e20-8095-b12facfe9502",
    "data": [
      {
        "text": "четвертый текст",
        "userDefined": false
      }
    ],
    "isTemplate": false,
    "count": 1,
    "updated": 0
  },
  {
    "id": "187abbe6-3792-46ce-811a-cd9d5f0ed270",
    "data": [
      {
        "text": "текст про рыбку",
        "userDefined": false
      }
    ],
    "isTemplate": false,
    "count": 0,
    "updated": 0
  },
  {
    "id": "f1555f01-6c32-41ad-b7f0-5a8c69a3c483",
    "data": [
      {
        "text": "текст про непростую рыбку",
        "userDefined": false
      }
    ],
    "isTemplate": false,
    "count": 0,
    "updated": 0
  },
  {
    "id": "8f627bb4-6e51-41a5-9588-b3e205537c8f",
    "data": [
      {
        "text": "Непростая рыбка",
        "userDefined": false
      }
    ],
    "isTemplate": false,
    "count": 0,
    "updated": 0
  },
  {
    "id": "09df8bb8-e419-42cb-bcb1-daecd8ca74ed",
    "data": [
      {
        "text": "4",
        "meta": "@sys.ignore",
        "userDefined": false
      },
      {
        "text": " текст",
        "userDefined": false
      }
    ],
    "isTemplate": false,
    "count": 0,
    "updated": 0
  },
  {
    "id": "ebaefd71-21c1-4298-ae2f-93abe2818e93",
    "data": [
      {
        "text": "давай ",
        "userDefined": false
      },
      {
        "text": "четвёртый",
        "meta": "@sys.ignore",
        "userDefined": false
      },
      {
        "text": " текст",
        "userDefined": false
      }
    ],
    "isTemplate": false,
    "count": 0,
    "updated": 0
  },
  {
    "id": "fdadbf66-0726-4648-8089-28a04a74f2c0",
    "data": [
      {
        "text": "четвёртый",
        "meta": "@sys.ignore",
        "userDefined": false
      },
      {
        "text": " текст",
        "userDefined": false
      }
    ],
    "isTemplate": false,
    "count": 0,
    "updated": 0
  }
]